valmath/__init__.py
valmath/add.py
valmath/divide.py
valmath/multiply.py
valmath/subtract.py
valmath/adv/__init__.py
valmath/adv/sqrt.py
valmath-0.2.dist-info/METADATA
valmath-0.2.dist-info/WHEEL
valmath-0.2.dist-info/top_level.txt
valmath-0.2.dist-info/RECORD
