Metadata-Version: 2.1
Name: valmath
Version: 0.2
Summary: A silly math package
Home-page: http://www.mymath.org/
Author: Mike Driscoll
Author-email: mike@mymath.org
License: UNKNOWN
Keywords: python,first package
Platform: UNKNOWN
Classifier: Development Status :: 3 - Alpha
Classifier: Intended Audience :: Education
Classifier: Programming Language :: Python :: 2
Classifier: Programming Language :: Python :: 3
Classifier: Operating System :: MacOS :: MacOS X
Classifier: Operating System :: Microsoft :: Windows
